blinker_herald/__init__.py
blinker_herald/base.py
blinker_herald-0.2.0.dist-info/DESCRIPTION.rst
blinker_herald-0.2.0.dist-info/METADATA
blinker_herald-0.2.0.dist-info/RECORD
blinker_herald-0.2.0.dist-info/WHEEL
blinker_herald-0.2.0.dist-info/metadata.json
blinker_herald-0.2.0.dist-info/top_level.txt
