Metadata-Version: 2.0
Name: blinker-herald
Version: 0.2.0
Summary: The Blinker Herald includes helpers to easily emit signals using Blinker. Decorate a function or method with @blinker_herald.emit() and pre and post signals will automatically be emitted to connected handlers.
Home-page: https://github.com/SatelliteQE/blinker_herald
Author: Bruno Rocha
Author-email: rochacbruno@gmail.com
License: ISCL
Keywords: blinker_herald
Platform: UNKNOWN
Classifier: Development Status :: 2 - Pre-Alpha
Classifier: Intended Audience :: Developers
Classifier: License :: OSI Approved :: ISC License (ISCL)
Classifier: Natural Language :: English
Classifier: Programming Language :: Python :: 2
Classifier: Programming Language :: Python :: 2.6
Classifier: Programming Language :: Python :: 2.7
Classifier: Programming Language :: Python :: 3
Classifier: Programming Language :: Python :: 3.3
Classifier: Programming Language :: Python :: 3.4
Classifier: Programming Language :: Python :: 3.5
